BooleanDictFilter/BooleanDictFilter.py
BooleanDictFilter/__init__.py
booleanDictFilter-1.0.2.dist-info/LICENSE
booleanDictFilter-1.0.2.dist-info/METADATA
booleanDictFilter-1.0.2.dist-info/WHEEL
booleanDictFilter-1.0.2.dist-info/top_level.txt
booleanDictFilter-1.0.2.dist-info/RECORD
