Metadata-Version: 2.1
Name: booleanDictFilter
Version: 1.0.2
Summary: Library for applying a boolean filter string to a dictionary, allowing for searches of keyvalue pairs.
Home-page: https://github.com/mrmessagewriter/BooleanDictFilter
Author: Sean Hummel
License: UNKNOWN
Platform: UNKNOWN
Classifier: Programming Language :: Python :: 3
Classifier: License :: OSI Approved :: MIT License
Classifier: Operating System :: OS Independent
Requires-Python: >=3.6
License-File: LICENSE
